HttpLibrary/__init__.py
HttpLibrary/livetest.py
robotframework_httplibrary3-0.6.0.dist-info/METADATA
robotframework_httplibrary3-0.6.0.dist-info/WHEEL
robotframework_httplibrary3-0.6.0.dist-info/top_level.txt
robotframework_httplibrary3-0.6.0.dist-info/RECORD
